rna_synthub/__init__.py
rna_synthub/py.typed
rna_synthub/analyze/__init__.py
rna_synthub/analyze/extract_angles.py
rna_synthub/analyze/extract_distance.py
rna_synthub/analyze/extractor_abstract.py
rna_synthub/analyze/script_example.py
rna_synthub/enum/__init__.py
rna_synthub/enum/angles.py
rna_synthub/enum/scoring_functions.py
rna_synthub/filter/__init__.py
rna_synthub/filter/extract_2d.py
rna_synthub/filter/locarna_helper.py
rna_synthub/filter/molprobity_helper.py
rna_synthub/filter/predict_abstract.py
rna_synthub/filter/rnaspider_helper.py
rna_synthub/filter/rnaspider_utils.py
rna_synthub/filter/selector.py
rna_synthub/filter/utils.py
rna_synthub/pdb_helper/__init__.py
rna_synthub/pdb_helper/sf_models.py
rna_synthub/viz/__init__.py
rna_synthub/viz/utils.py
rna_synthub/viz/viz_angles.py
rna_synthub/viz/viz_cli.py
rna_synthub/viz/viz_distance.py
rna_synthub/viz/viz_funnel.py
rna_synthub/viz/viz_helper.py
rna_synthub/viz/viz_sf.py
rna_synthub-0.1.0.dist-info/METADATA
rna_synthub-0.1.0.dist-info/WHEEL
rna_synthub-0.1.0.dist-info/entry_points.txt
rna_synthub-0.1.0.dist-info/RECORD
