Metadata-Version: 2.4
Name: rna-synthub
Version: 0.1.0
Summary: Add your description here
Author-email: clementbernardd <clementbernardd@gmail.com>
Requires-Python: >=3.10
Requires-Dist: click>=8.3.0
Requires-Dist: kaleido>=1.1.0
Requires-Dist: pandas>=2.3.2
Requires-Dist: plotly>=6.3.0
Requires-Dist: requests>=2.32.5
Requires-Dist: rnadvisor>=2.1.8
Requires-Dist: scikit-learn>=1.7.2
Requires-Dist: torch>=2.0.0
